beancount_mnb/__init__.py
beancount_mnb-1.0.1.dist-info/LICENSE
beancount_mnb-1.0.1.dist-info/METADATA
beancount_mnb-1.0.1.dist-info/WHEEL
beancount_mnb-1.0.1.dist-info/top_level.txt
beancount_mnb-1.0.1.dist-info/RECORD
