Metadata-Version: 2.1
Name: beancount-mnb
Version: 1.0.1
Summary: Az MNB hivatalos középárfolyamainak letöltését megvalósító beancount plugin.
Home-page: https://github.com/belidzs/beancount_mnb
Author: Balázs Keresztury
License: MIT
Keywords: beancount importer mnb currency
Platform: UNKNOWN
Classifier: Development Status :: 5 - Production/Stable
Classifier: License :: OSI Approved :: MIT License
Classifier: Operating System :: OS Independent
Classifier: Environment :: Plugins
Classifier: Natural Language :: Hungarian
Classifier: Topic :: Office/Business :: Financial :: Accounting
Requires-Dist: beancount (>=2.2.1)
Requires-Dist: zeep (>=3.2.0)
Requires-Dist: pytz (>=2018.9)
Requires-Dist: lxml (>=4.3.2)
